numpy_onlinestats/__init__.py
numpy_onlinestats/_numpy_onlinestats_impl.cpython-311-x86_64-linux-gnu.so
numpy_onlinestats/_version.py
numpy_onlinestats.libs/libgomp-a34b3233.so.1.0.0
numpy_onlinestats-0.1.1.dist-info/METADATA
numpy_onlinestats-0.1.1.dist-info/WHEEL
numpy_onlinestats-0.1.1.dist-info/RECORD
numpy_onlinestats-0.1.1.dist-info/licenses/LICENSE
