Metadata-Version: 2.2
Name: numpy-onlinestats
Version: 0.1.1
Summary: Online statistics for Numpy arrays.
Author: Ilia Kats
Maintainer-Email: Ilia Kats <ilia-kats@gmx.net>
License:                     GNU GENERAL PUBLIC LICENSE
Classifier: Intended Audience :: Science/Research
Classifier: Operating System :: OS Independent
Classifier: Programming Language :: C++
Classifier: Topic :: Scientific/Engineering
Project-URL: Documentation, https://numpy-onlinestats.readthedocs.io/
Project-URL: Source, https://github.com/ilia-kats/numpy-onlinestats
Project-URL: Home-page, https://github.com/ilia-kats/numpy-onlinestats
Requires-Python: >=3.10
Requires-Dist: numpy
Provides-Extra: test
Requires-Dist: scipy; extra == "test"
Requires-Dist: pytest; extra == "test"
Requires-Dist: pytest-cov; extra == "test"
Provides-Extra: doc
Requires-Dist: docutils!=0.18.*,!=0.19.*,>=0.8; extra == "doc"
Requires-Dist: sphinx>=4; extra == "doc"
Requires-Dist: sphinx-book-theme>=1.0.0; extra == "doc"
Requires-Dist: sphinx-autodoc-typehints; extra == "doc"
Requires-Dist: myst-parser; extra == "doc"
